funmcp/__init__.py
funmcp/mcp/__init__.py
funmcp-0.0.3.dist-info/METADATA
funmcp-0.0.3.dist-info/WHEEL
funmcp-0.0.3.dist-info/top_level.txt
funmcp-0.0.3.dist-info/RECORD
