Metadata-Version: 2.4
Name: funmcp
Version: 0.0.3
Summary: funmcp
Author-email: niuliangtao <farfarfun@qq.com>
Requires-Python: >=3.8
